jsobj/__init__.py
jsobj/jsobj.py
jsobj-1.0.4.dist-info/DESCRIPTION.rst
jsobj-1.0.4.dist-info/METADATA
jsobj-1.0.4.dist-info/metadata.json
jsobj-1.0.4.dist-info/RECORD
jsobj-1.0.4.dist-info/top_level.txt
jsobj-1.0.4.dist-info/WHEEL
