Metadata-Version: 2.0
Name: jsobj
Version: 1.0.4
Summary: Jsobj provides JavaScript-Style Objects                  in Python.
Home-page: https://github.com/gkovacs/jsobj
Author: Geza Kovacs
Author-email: geza0kovacs@gmail.com
License: MIT
Keywords: jsobj,Object,json,chain,javascript
Platform: any
Classifier: Development Status :: 4 - Beta
Classifier: Intended Audience :: Developers
Classifier: License :: OSI Approved :: MIT License
Classifier: Operating System :: OS Independent
Classifier: Programming Language :: Python :: 2.6
Classifier: Programming Language :: Python :: 2.7
Classifier: Programming Language :: Python :: 3
Classifier: Programming Language :: Python :: 3.2
Classifier: Programming Language :: Python :: 3.3
Classifier: Programming Language :: Python :: 3.4
Classifier: Programming Language :: Python
Classifier: Topic :: Software Development :: Libraries
Classifier: Topic :: Software Development
Classifier: Topic :: Utilities
